betterlog/__init__.py
betterlog/betterlog.py
betterlog-0.0.2.dist-info/License.txt
betterlog-0.0.2.dist-info/METADATA
betterlog-0.0.2.dist-info/WHEEL
betterlog-0.0.2.dist-info/top_level.txt
betterlog-0.0.2.dist-info/RECORD
